aisys/__init__.py
aisys/conversational.py
aisys/int_tts.py
aisys/logs/.gitkeep
aisys/main.py
aisys-0.1.0.dist-info/METADATA
aisys-0.1.0.dist-info/WHEEL
aisys-0.1.0.dist-info/entry_points.txt
aisys-0.1.0.dist-info/RECORD
