Metadata-Version: 2.3
Name: aisys
Version: 0.1.0
Summary: lil' ai buddy
Author: Kokonico
Author-email: kokonico@duck.com
Requires-Python: >=3.13,<4.0
Classifier: Programming Language :: Python :: 3
Classifier: Programming Language :: Python :: 3.13
Requires-Dist: duckduckgo-search (>=6.4.2,<7.0.0)
Requires-Dist: ollama (>=0.4.2,<0.5.0)
Requires-Dist: schedule (>=1.2.2,<2.0.0)
